README.rst
setup.py
skrt/__init__.py
skrt/containers.py
skrt/functional.py
skrt/iterators.py
skrt/text.py
skrt/utils.py
skrt.egg-info/PKG-INFO
skrt.egg-info/SOURCES.txt
skrt.egg-info/dependency_links.txt
skrt.egg-info/top_level.txt