Metadata-Version: 1.2
Name: skrt
Version: 1.3.2.1
Summary: Nifty tools and containers
Home-page: https://github.com/nvander1/skrt
Author: Nik Vanderhoof
Author-email: pypi@vanderhoof.pw
License: MIT
Keywords: development tools containers
Platform: UNKNOWN
Classifier: Development Status :: 3 - Alpha
Classifier: Intended Audience :: Developers
Classifier: License :: OSI Approved :: MIT License
Classifier: Programming Language :: Python :: 2.7
Requires-Python: >=2.7
